{"trial_id": "10", "hyperparameters": {"space": [{"class_name": "Choice", "config": {"name": "dropout1", "default": 0.3, "conditions": [], "values": [0.3, 0.4, 0.5], "ordered": true}}, {"class_name": "Choice", "config": {"name": "dropout2", "default": 0.2, "conditions": [], "values": [0.2, 0.3, 0.4], "ordered": true}}, {"class_name": "Choice", "config": {"name": "learning_rate", "default": 0.0001, "conditions": [], "values": [0.0001, 0.001, 0.01], "ordered": true}}], "values": {"dropout1": 0.3, "dropout2": 0.2, "learning_rate": 0.0001}}, "metrics": {"metrics": {"accuracy": {"direction": "max", "observations": [{"value": [0.8801295757293701], "step": 29}]}, "loss": {"direction": "min", "observations": [{"value": [0.25638991594314575], "step": 29}]}, "val_accuracy": {"direction": "max", "observations": [{"value": [0.867625892162323], "step": 29}]}, "val_loss": {"direction": "min", "observations": [{"value": [0.2685551941394806], "step": 29}]}}}, "score": 0.867625892162323, "best_step": 29, "status": "COMPLETED", "message": null}